sarunasncalculator/__init__.py
sarunasncalculator/calculator.py
sarunasncalculator-0.4.5.dist-info/WHEEL
sarunasncalculator-0.4.5.dist-info/METADATA
sarunasncalculator-0.4.5.dist-info/RECORD
