Metadata-Version: 2.1
Name: sarunasncalculator
Version: 0.4.5
Summary: 1st sprint project Turing College Calculator
Author: Sarunas Noreika
Author-email: sarunas.nor@gmail.com
Classifier: License :: OSI Approved :: MIT License
